License.txt
setup.cfg
setup.py
yungestWeb/__init__.py
yungestWeb/app.py
yungestWeb/reader_file.py
yungestWeb/request.py
yungestWeb/response.py
yungestWeb/router.py
yungestWeb/runner.py
yungestWeb.egg-info/PKG-INFO
yungestWeb.egg-info/SOURCES.txt
yungestWeb.egg-info/dependency_links.txt
yungestWeb.egg-info/top_level.txt