Metadata-Version: 2.1
Name: yungestWeb
Version: 0.0.5
Summary: This is a web-framework to help python developers join web delevopment, have fun!
Author: yungestDev
Author-email: yungestmonsterhahaha@gmail.com
License: MIT
Keywords: WebFramework,Framework
Platform: UNKNOWN
Classifier: Development Status :: 3 - Alpha
Classifier: Intended Audience :: Developers
Classifier: Topic :: Software Development :: Build Tools
Classifier: License :: OSI Approved :: MIT License
Classifier: Programming Language :: Python :: 3.10
License-File: License.txt
